{
    "pools": [
      {
        "name": "zombieloot:police_ammo_shelf",
        "rolls": {
          "min": 0,
          "max": 10
        },
        "entries": [
          {
            "type": "item",
            "name": "cgm:short_scope",
            "functions": [
              {
                "function": "set_count",
                "count": {
                  "min": 0,
                  "max": 1
                }
              }
            ],
            "weight": 10
          },
          {
            "type": "item",
            "name": "cgm:medium_scope",
            "functions": [
              {
                "function": "set_count",
                "count": {
                  "min": 0,
                  "max": 1
                }
              }
            ],
            "weight": 10
          },
          {
            "type": "item",
            "name": "cgm:long_scope",
            "functions": [
              {
                "function": "set_count",
                "count": {
                  "min": 0,
                  "max": 1
                }
              }
            ],
            "weight": 10
          },
  
  
          {
            "type": "item",
            "name": "cgm:light_stock",
            "functions": [
              {
                "function": "set_count",
                "count": {
                  "min": 0,
                  "max": 1
                }
              }
            ],
            "weight": 10
          },
          {
            "type": "item",
            "name": "cgm:tactical_stock",
            "functions": [
              {
                "function": "set_count",
                "count": {
                  "min": 0,
                  "max": 1
                }
              }
            ],
            "weight": 10
          },
  
  
          {
            "type": "item",
            "name": "cgm:light_grip",
            "functions": [
              {
                "function": "set_count",
                "count": {
                  "min": 0,
                  "max": 1
                }
              }
            ],
            "weight": 10
          },
          {
            "type": "item",
            "name": "cgm:specialised_grip",
            "functions": [
              {
                "function": "set_count",
                "count": {
                  "min": 0,
                  "max": 1
                }
              }
            ],
            "weight": 10
          },
  
  
          {
            "type": "item",
            "name": "cgm:silencer",
            "functions": [
              {
                "function": "set_count",
                "count": {
                  "min": 0,
                  "max": 1
                }
              }
            ],
            "weight": 5
          },
  
  
  
          {
            "type": "item",
            "name": "cgm:basic_bullet",
            "functions": [
              {
                "function": "set_count",
                "count": {
                  "min": 3,
                  "max": 7
                }
              }
            ],
            "weight": 50
          },
          {
            "type": "item",
            "name": "cgm:shell",
            "functions": [
              {
                "function": "set_count",
                "count": {
                  "min": 3,
                  "max": 7
                }
              }
            ],
            "weight": 30
          },
          {
            "type": "item",
            "name": "cgm:advanced_bullet",
            "functions": [
              {
                "function": "set_count",
                "count": {
                  "min": 2,
                  "max": 4
                }
              }
            ],
            "weight": 15
          },
  
          {
            "type": "item",
            "name": "cgm:grenade",
            "functions": [
              {
                "function": "set_count",
                "count": {
                  "min": 0,
                  "max": 3
                }
              }
            ],
            "weight": 10
          },
          {
            "type": "item",
            "name": "minecraft:air",
            "weight": 40
          }
        ]
      }
    ]
  }